PyVecs/__init__.py
PyVecs/main.py
pyvecs-0.0.8.dist-info/METADATA
pyvecs-0.0.8.dist-info/WHEEL
pyvecs-0.0.8.dist-info/top_level.txt
pyvecs-0.0.8.dist-info/RECORD
