Metadata-Version: 2.4
Name: PyVecs
Version: 0.0.8
Summary: A simple 2D and 3D Vector class to Python.
Author: Thales Rodrigues
Author-email: thaleshend@gmail.com
Project-URL: Github, https://github.com/Thales625/PyVecs
Classifier: Development Status :: 3 - Alpha
Classifier: Intended Audience :: Developers
Classifier: Programming Language :: Python :: 3.10
Classifier: Programming Language :: Python :: 3.11
Classifier: Topic :: Utilities
Requires-Python: >=3.10
Dynamic: author
Dynamic: author-email
Dynamic: classifier
Dynamic: description
Dynamic: description-content-type
Dynamic: project-url
Dynamic: requires-python
Dynamic: summary
